resoto_plugin_gcp/__init__.py
resoto_plugin_gcp/collector.py
resoto_plugin_gcp/config.py
resoto_plugin_gcp/gcp_client.py
resoto_plugin_gcp/utils.py
resoto_plugin_gcp/resources/__init__.py
resoto_plugin_gcp/resources/base.py
resoto_plugin_gcp/resources/billing.py
resoto_plugin_gcp/resources/compute.py
resoto_plugin_gcp/resources/container.py
resoto_plugin_gcp/resources/sqladmin.py
resoto_plugin_gcp/resources/storage.py
test/__init__.py
test/conftest.py
test/random_client.py
test/test_base.py
test/test_billing.py
test/test_collector.py
test/test_compute.py
test/test_config.py
test/test_container.py
test/test_sqladmin.py
test/test_storage.py
resoto_plugin_gcp-3.9.0.dist-info/METADATA
resoto_plugin_gcp-3.9.0.dist-info/WHEEL
resoto_plugin_gcp-3.9.0.dist-info/entry_points.txt
resoto_plugin_gcp-3.9.0.dist-info/top_level.txt
resoto_plugin_gcp-3.9.0.dist-info/RECORD
